kparc/__init__.py
kparc-0.0.1rc1.dist-info/METADATA
kparc-0.0.1rc1.dist-info/WHEEL
kparc-0.0.1rc1.dist-info/top_level.txt
kparc-0.0.1rc1.dist-info/RECORD
