Metadata-Version: 2.1
Name: kparc
Version: 0.0.1rc1
Summary: k for python
Home-page: https://kparc.io
Author: regents of kparc
Author-email: a@kparc.io
License: UNKNOWN
Platform: UNKNOWN
Classifier: Programming Language :: Python :: 3
Classifier: License :: OSI Approved :: MIT License
Classifier: Operating System :: OS Independent
Requires-Python: >=3.7
